README.md
setup.cfg
setup.py
pyvpn/__init__.py
pyvpn/pyvpn.py
pyvpn/source/__init__.py
pyvpn/source/client.py
pyvpn/source/crypt.py
pyvpn/source/providers.py
pyvpn/source/routes.py
pyvpn/source/vpn.py
vpnpy.egg-info/PKG-INFO
vpnpy.egg-info/SOURCES.txt
vpnpy.egg-info/dependency_links.txt
vpnpy.egg-info/requires.txt
vpnpy.egg-info/top_level.txt